{
  "name": "PlanMateriaView",
  "base": "PersistedModel",
  "idInjection": true,
  "options": {
    "validateUpsert": true
  },
  "properties": {
    "idPlanEstudio": {
      "type": "number",
      "id": true
    },
    "idNivel": {
      "type": "number"
    },
    "nombrePlan": {
      "type": "string"
    },
    "idPlanMateria": {
      "type": "number"
    },
    "anio": {
      "type": "string"
    },
    "codMateria": {
      "type": "number"
    },
    "nombreMateria": {
      "type": "string"
    }
  },
  "validations": [],
  "relations": {},
  "acls": [],
  "methods": {}
}
